COPYING_EMOJI4UNICODE
COPYING_ICU
COPYING_TYPEPAD
COPYING_UNICODE
MANIFEST.in
README
setup.py
bpmobile/__init__.py
bpmobile/context_processors.py
bpmobile/decorators.py
bpmobile/middleware.py
bpmobile/models.py
bpmobile/test.py
bpmobile/tests.py
bpmobile/utils.py
bpmobile/wsgi.py
bpmobile/data/emoji2image.xml
bpmobile/data/emoji4unicode.xml
bpmobile/data/arib/arib.ucm
bpmobile/data/docomo/carrier_data.xml
bpmobile/data/icu/windows-932-2000.ucm
bpmobile/data/kddi/carrier_data.xml
bpmobile/data/softbank/carrier_data.xml
bpmobile/e4u/__init__.py
bpmobile/e4u/arib2ucm.py
bpmobile/e4u/carrier_data.py
bpmobile/e4u/carrier_data_test.py
bpmobile/e4u/emoji4unicode.py
bpmobile/e4u/emoji4unicode_test.py
bpmobile/e4u/gen_html.py
bpmobile/e4u/report_img_from.py
bpmobile/e4u/row_cell.py
bpmobile/e4u/row_cell_test.py
bpmobile/e4u/ucm.py
bpmobile/e4u/unicode_names.py
bpmobile/e4u/unicode_names_test.py
bpmobile/e4u/utf.py
bpmobile/management/__init__.py
bpmobile/management/commands/__init__.py
bpmobile/management/commands/runserver_imode.py
bpmobile/media/img/emoticons/24hours.gif
bpmobile/media/img/emoticons/airplane.gif
bpmobile/media/img/emoticons/angry.gif
bpmobile/media/img/emoticons/annoy.gif
bpmobile/media/img/emoticons/apple.gif
bpmobile/media/img/emoticons/appli01.gif
bpmobile/media/img/emoticons/appli02.gif
bpmobile/media/img/emoticons/aquarius.gif
bpmobile/media/img/emoticons/aries.gif
bpmobile/media/img/emoticons/art.gif
bpmobile/media/img/emoticons/atm.gif
bpmobile/media/img/emoticons/bag.gif
bpmobile/media/img/emoticons/ban.gif
bpmobile/media/img/emoticons/banana.gif
bpmobile/media/img/emoticons/bank.gif
bpmobile/media/img/emoticons/bar.gif
bpmobile/media/img/emoticons/baseball.gif
bpmobile/media/img/emoticons/basketball.gif
bpmobile/media/img/emoticons/bearing.gif
bpmobile/media/img/emoticons/beer.gif
bpmobile/media/img/emoticons/bell.gif
bpmobile/media/img/emoticons/bicycle.gif
bpmobile/media/img/emoticons/birthday.gif
bpmobile/media/img/emoticons/bleah.gif
django_bpmobile.egg-info/PKG-INFO
django_bpmobile.egg-info/SOURCES.txt
django_bpmobile.egg-info/dependency_links.txt
django_bpmobile.egg-info/not-zip-safe
django_bpmobile.egg-info/requires.txt
django_bpmobile.egg-info/top_level.txt