Metadata-Version: 1.0
Name: django-bpmobile
Version: 0.1
Summary: A helper application for Japanese mobile phones.
Home-page: http://bitbucket.org/tokibito/django-bpmobile/
Author: Shinya Okano
Author-email: tokibito@gmail.com
License: BSD License
Platform: UNKNOWN
Classifier: Development Status :: 3 - Alpha
Classifier: Environment :: Plugins
Classifier: Framework :: Django
Classifier: Intended Audience :: Developers
Classifier: License :: OSI Approved :: BSD License
Classifier: Programming Language :: Python
Classifier: Topic :: Software Development :: Libraries :: Python Modules
